Metadata-Version: 2.4
Name: ikiss
Version: 2.0.0
Summary: iKISS is a pipeline to detect kmers under selection.
Author-email: "Julie Orjuela (DIADE-IRD)" <julie.orjuela@ird.fr>
License-Expression: GPL-3.0-or-later
Project-URL: Homepage, https://forge.ird.fr/diade/iKISS.git
Project-URL: Documentation, https://ikiss.readthedocs.io/en/latest/
Project-URL: repository, https://forge.ird.fr/diade/iKISS.git
Project-URL: Downloads, https://forge.ird.fr/diade/iKISS/-/releases/
Project-URL: Bug Tracker, https://forge.ird.fr/diade/iKISS/-/issues
Project-URL: Source Code, https://forge.ird.fr/diade/iKISS.git
Keywords: snakemake,kmers,selection,diversity,structure,association
Classifier: Development Status :: 5 - Production/Stable
Classifier: Intended Audience :: Developers
Classifier: Intended Audience :: End Users/Desktop
Classifier: Operating System :: POSIX :: Linux
Classifier: Programming Language :: Python :: 3.12
Classifier: Programming Language :: Python :: 3.12
Classifier: Programming Language :: R
Classifier: Natural Language :: English
Classifier: Topic :: Scientific/Engineering
Classifier: Topic :: Scientific/Engineering :: Bio-Informatics
Requires-Python: >=3.11
License-File: LICENCE
License-File: AUTHORS.md
Requires-Dist: pandas
Requires-Dist: matplotlib
Requires-Dist: tabulate
Requires-Dist: ipython
Requires-Dist: biopython
Requires-Dist: pysam
Requires-Dist: numpy
Requires-Dist: snakecdysis==2.0.1
Requires-Dist: setuptools>=68.2.0
Requires-Dist: snakemake
Requires-Dist: nbformat
Requires-Dist: PyYAML
Requires-Dist: pandas
Requires-Dist: matplotlib
Requires-Dist: tabulate
Requires-Dist: ipython
Requires-Dist: biopython
Requires-Dist: numpy
Requires-Dist: argparse
Requires-Dist: tqdm
Provides-Extra: docs
Requires-Dist: sphinx; extra == "docs"
Requires-Dist: sphinx_click; extra == "docs"
Requires-Dist: sphinx_copybutton; extra == "docs"
Requires-Dist: sphinx_rtd_theme; extra == "docs"
Requires-Dist: sphinx_automodapi; extra == "docs"
Requires-Dist: sphinx_design; extra == "docs"
Requires-Dist: myst_parser; extra == "docs"
Requires-Dist: tox; extra == "docs"
Requires-Dist: click_extra; extra == "docs"
Requires-Dist: pygments_ansi_color; extra == "docs"
Requires-Dist: sphinx_rtd_theme; extra == "docs"
Provides-Extra: dev
Requires-Dist: setuptools>=68.2.0; extra == "dev"
Dynamic: license-file
